<?xml version="1.0"?>
<cm:cthulhuMythos xmlns:xsi="http://www.w3.org/2001/XMLSchema-instance"
    xsi:schemaLocation="https://github.com/lewca/Cthulhu-Mythos http://www.pitt.edu/~mkane/CthulhuMythos/Cthulhu-Mythos.xsd"
    xmlns:mods="http://www.loc.gov/mods/v3" xmlns:dcterms="http://purl.org/dc/terms/"
    xmlns:cm="https://github.com/lewca/Cthulhu-Mythos" xmlns:dc="http://purl.org/dc/elements/1.1/">
    <cm:modsSection>
        <mods:mods>
    <mods:titleInfo>
    <mods:title>The Ballad of Black Tom</mods:title>
</mods:titleInfo>
<mods:name type="personal" authority="naf" authorityURI="http://id.loc.gov/authorities/names/n80017007">
    <mods:namePart type="family">LaValle</mods:namePart>
    <mods:namePart type="given">Victor</mods:namePart>
    <mods:namePart type="date">1972-</mods:namePart>   
    <mods:role>
        <mods:roleTerm type="code" authority="marcrelator">aut</mods:roleTerm>
        <mods:roleTerm type="text" authority="marcrelator">Author</mods:roleTerm>
    </mods:role> 
    <mods:description>American author, 21st c.</mods:description>
    <mods:role>
        <mods:roleTerm type="text" authority="marcrelator">creator</mods:roleTerm>
        <mods:roleTerm type="code" authority="marcrelator">cre</mods:roleTerm>
    </mods:role>
</mods:name>
<mods:typeOfResource>text</mods:typeOfResource>
<mods:language>
    <mods:languageTerm>eng</mods:languageTerm>
</mods:language>
<mods:originInfo>    
    <mods:dateCreated encoding="iso8601">2016</mods:dateCreated>
</mods:originInfo>
<mods:abstract>The Ballad of Black Tom is a 2016 fantasy/horror novella by Victor LaValle, revisiting H.P. Lovecraft's story "The Horror at Red Hook" from the viewpoint of a black man. </mods:abstract>
<mods:subject authority="lcsh">
    <mods:topic>LaValle, Victor, 1972</mods:topic>
</mods:subject>
<mods:subject>
    <mods:topic>Lovecraft, H. P. (Howard Phillips), 1890-1937--Appreciation</mods:topic>
</mods:subject>
<mods:subject>
    <mods:topic>Novella</mods:topic>
</mods:subject>
<mods:subject authority="lcsh">
    <mods:topic>Horror tales, American</mods:topic>
</mods:subject>
<mods:subject authority="lcsh">
    <mods:topic>Fantasy fiction, American</mods:topic>
</mods:subject>
<mods:genre authority="marcgt">short story</mods:genre>
<mods:genre authority="marcgt">fiction</mods:genre>
<mods:location displayLabel="Cthulhu Mythos">
    <mods:shelfLocator>CM11</mods:shelfLocator>
</mods:location>
<mods:relatedItem type="otherFormat">
    <mods:physicalDescription>
        <mods:internetMediaType>book</mods:internetMediaType>
        <mods:extent>149 pages</mods:extent>
        <mods:form>ISBN 13: 9780765387868</mods:form>
    </mods:physicalDescription>
</mods:relatedItem>
<mods:relatedItem type="host">
    <mods:titleInfo>
        <mods:title>The Ballad of Black Tom</mods:title>
    </mods:titleInfo>  
</mods:relatedItem>
<mods:accessCondition>The item is under copyright.</mods:accessCondition>
</mods:mods>
    </cm:modsSection>
    <cm:dcSection>
        <dcterms:title>The Ballad of Black Tom</dcterms:title>
        <dc:creator>Lovecraft, H. P. (Howard Phillips)</dc:creator>
        <dcterms:type>text</dcterms:type>
        <dcterms:subject>Cthulhu Mythos</dcterms:subject>
        <dcterms:rights>copyright</dcterms:rights>
    </cm:dcSection>
</cm:cthulhuMythos>